jmstorage/__init__.py
jmstorage/client.py
jmstorage/constants.py
jmstorage/storage/__init__.py
jmstorage/storage/base.py
jmstorage/storage/disk_storage_manager.py
jmstorage/storage/redis_storage_manager.py
jmstorage-0.0.1.dist-info/LICENSE
jmstorage-0.0.1.dist-info/METADATA
jmstorage-0.0.1.dist-info/WHEEL
jmstorage-0.0.1.dist-info/top_level.txt
jmstorage-0.0.1.dist-info/RECORD
