Metadata-Version: 2.1
Name: jmstorage
Version: 0.0.1
Summary: Key value caching machanism with backends: disk, Sqlite, Redis, MySQL, PostgreSQL.
Author: JustinMusti
License: MIT License
Project-URL: Homepage, https://github.com/justinmusti/jmstorage
Project-URL: Bug Tracker, https://github.com/justinmusti/jmstorage/issues
Classifier: Development Status :: 3 - Alpha
Classifier: License :: OSI Approved :: MIT License
Classifier: Operating System :: OS Independent
Classifier: Programming Language :: Python :: 3.8
Classifier: Programming Language :: Python :: 3.9
Classifier: Programming Language :: Python :: 3.10
Classifier: Programming Language :: Python :: 3.11
Classifier: Programming Language :: Python :: 3.12
Classifier: Programming Language :: Python :: 3.13
Requires-Python: >=3.8
License-File: LICENSE
Requires-Dist: dill ~=0.3
Provides-Extra: dev
Requires-Dist: build ~=1.0 ; extra == 'dev'
Requires-Dist: flake8 ~=6.1 ; extra == 'dev'
Requires-Dist: isort ==5.12.0 ; extra == 'dev'
Requires-Dist: ipython ~=8.12 ; extra == 'dev'
Requires-Dist: pytest ==7.4.3 ; extra == 'dev'
Requires-Dist: twine ==4.0.2 ; extra == 'dev'
